{
    "attributes": {
        "_description": {
            "key": "_description",
            "type": "STRING",
            "value": "<p xmlns=\"http://www.w3.org/1999/xhtml\" class=\"table-indent\" style=\"page-break-after: avoid;\"><span lang=\"EN-US\" style=\"font-family: Symbol;\"><span style=\"font: 7pt &quot;Times New Roman&quot;;\">      \n  <\/span><\/span><span lang=\"EN-US\">memory<\/span><\/p>\n  <p xmlns=\"http://www.w3.org/1999/xhtml\" class=\"table-indent\" style=\"page-break-after: avoid;\"><span lang=\"EN-US\" style=\"font-family: Symbol;\">·<span style=\"font: 7pt &quot;Times New Roman&quot;;\">        \n  <\/span><\/span><span lang=\"EN-US\">bus<\/span><\/p>\n  <p xmlns=\"http://www.w3.org/1999/xhtml\" class=\"table-indent\" style=\"page-break-after: avoid;\"><span lang=\"EN-US\" style=\"font-family: Symbol;\">·<span style=\"font: 7pt &quot;Times New Roman&quot;;\">        \n  <\/span><\/span><span lang=\"EN-US\">virtual processor<\/span><\/p>\n  <p xmlns=\"http://www.w3.org/1999/xhtml\" class=\"table-indent\" style=\"page-break-after: avoid;\"><span lang=\"EN-US\" style=\"font-family: Symbol;\">·<span style=\"font: 7pt &quot;Times New Roman&quot;;\">        \n  <\/span><\/span><span lang=\"EN-US\">virtual bus<\/span><\/p>\n  <p xmlns=\"http://www.w3.org/1999/xhtml\" class=\"table-indent\" style=\"page-break-after: avoid;\"><span lang=\"EN-US\" style=\"font-family: Symbol;\">·<span style=\"font: 7pt &quot;Times New Roman&quot;;\">        \n  <\/span><\/span><span lang=\"EN-US\">abstract<\/span><\/p>"
        },
        "_type": {
            "key": "_type",
            "type": "STRING",
            "value": "Location"
        }
    },
    "uuid": "e93c6bb8-a10c-4803-89d4-7af898f18ce9"
}