{
    "attributes": {
        "_author": {
            "key": "_author",
            "type": "STRING",
            "value": "gerlits"
        },
        "_description": {
            "key": "_description",
            "type": "STRING",
            "value": "<p>\n\t-- An alias declaration renames all declarations of the containing package. The public section of<br />\n\t-- the containing package contains some component implementation<br />\n\t-- declarations. No bug SC0026.<br />\n\tPACKAGE TC5<br />\n\t&nbsp;&nbsp; &nbsp;PUBLIC<br />\n\t&nbsp;&nbsp; &nbsp;&nbsp;&nbsp; &nbsp;WITH COMPONENT_TYPES;<br />\n\t&nbsp;&nbsp; &nbsp;&nbsp;&nbsp; &nbsp;renames TC5::all; -- No bug SC0026<br />\n\t&nbsp;&nbsp; &nbsp;&nbsp;&nbsp; &nbsp;<br />\n\t&nbsp;&nbsp; &nbsp;&nbsp;&nbsp; &nbsp;PROCESS IMPLEMENTATION processT.impl<br />\n\t&nbsp;&nbsp; &nbsp;&nbsp;&nbsp; &nbsp;END&nbsp;&nbsp; &nbsp;processT.impl;<br />\n\t&nbsp;&nbsp; &nbsp;&nbsp;&nbsp; &nbsp;<br />\n\t&nbsp;&nbsp; &nbsp;&nbsp;&nbsp; &nbsp;PROCESSOR IMPLEMENTATION processorT.impl<br />\n\t&nbsp;&nbsp; &nbsp;&nbsp;&nbsp; &nbsp;END&nbsp;&nbsp; &nbsp;processorT.impl;<br />\n\t&nbsp;&nbsp; &nbsp;&nbsp;&nbsp; &nbsp;&nbsp;&nbsp; &nbsp;&nbsp;&nbsp; &nbsp;&nbsp;&nbsp; &nbsp;&nbsp;&nbsp; &nbsp;&nbsp;&nbsp; &nbsp;&nbsp;&nbsp; &nbsp;<br />\n\t&nbsp;&nbsp; &nbsp;PRIVATE&nbsp;&nbsp; &nbsp;&nbsp;&nbsp; &nbsp;<br />\n\t&nbsp;&nbsp; &nbsp;&nbsp;&nbsp; &nbsp;renames TC5::all; -- No bug SC0026&nbsp;&nbsp; &nbsp;&nbsp;&nbsp; &nbsp;&nbsp;&nbsp; &nbsp;&nbsp;&nbsp; &nbsp;&nbsp;&nbsp; &nbsp;&nbsp;&nbsp; &nbsp;<br />\n\tEND TC5;<\/p>\n<p>\n\t&nbsp;<\/p>\n<p>\n\tPACKAGE COMPONENT_TYPES<br />\n\t&nbsp;&nbsp; &nbsp;PUBLIC<br />\n\t&nbsp;&nbsp; &nbsp;&nbsp;&nbsp; &nbsp;PROCESS processT<br />\n\t&nbsp;&nbsp; &nbsp;&nbsp;&nbsp; &nbsp;END processT;<br />\n\t&nbsp;&nbsp; &nbsp;&nbsp;&nbsp; &nbsp;<br />\n\t&nbsp;&nbsp; &nbsp;&nbsp;&nbsp; &nbsp;PROCESSOR processorT<br />\n\t&nbsp;&nbsp; &nbsp;&nbsp;&nbsp; &nbsp;END processorT;<br />\n\tEND COMPONENT_TYPES;<\/p>\n"
        },
        "_expectedResults": {
            "key": "_expectedResults",
            "type": "STRING",
            "value": ""
        },
        "_status": {
            "key": "_status",
            "type": "STRING",
            "value": "complete"
        },
        "_type": {
            "key": "_type",
            "type": "STRING",
            "value": "TestPurpose"
        }
    },
    "uuid": "db4f3c91-b2d5-4105-97e6-2bcf56b823be"
}